[
  {
    "name": "Si Jalak Harupat",
    "open_days": [0, 1, 2, 3, 4, 5, 6],
    "open_at": "8:00",
    "closed_at": "23:59",
    "timezone": "Asia/Jakarta",
    "supported_events": [
      {
        "id": 2,
        "name": "Exhibition",
        "meetups_capacity": 1
      },
      {
        "id": 3,
        "name": "Bazaar",
        "meetups_capacity": 1
      },
      {
        "id": 4,
        "name": "Workshop",
        "meetups_capacity": 1
      }
    ]
  },
  {
    "name": "Parahyangan Convention",
    "open_days": [0, 1, 3, 4, 5, 6],
    "open_at": "00:00",
    "closed_at": "23:59",
    "timezone": "Asia/Jakarta",
    "supported_events": [
      {
        "id": 1,
        "name": "Wedding",
        "meetups_capacity": 1
      },
      {
        "id": 2,
        "name": "Exhibition",
        "meetups_capacity": 1
      }
    ]
  },
  {
    "name": "Ice BSD",
    "open_days": [0, 1, 2, 3, 4, 5, 6],
    "open_at": "05:00",
    "closed_at": "23:59",
    "timezone": "Asia/Jakarta",
    "supported_events": [
      {
        "id": 1,
        "name": "Wedding",
        "meetups_capacity": 1
      },
      {
        "id": 2,
        "name": "Exhibition",
        "meetups_capacity": 2
      },
      {
        "id": 3,
        "name": "Bazaar",
        "meetups_capacity": 2
      },
      {
        "id": 4,
        "name": "Workshop",
        "meetups_capacity": 3
      },
      {
        "id": 5,
        "name": "Conference",
        "meetups_capacity": 2
      }
    ]
  }
]
